{
  "name": "Mangoswap Default List",
  "timestamp": "2021-03-17T09:56:23Z",
  "version": {
    "major": 2,
    "minor": 10,
    "patch": 0
  },
  "tags": {},
  "logoURI": "https://cdridge.oss-cn-shanghai.aliyuncs.com/telegram_pocket/TX.png",
  "keywords": [
    "pancake",
    "default"
  ],
  "tokens": [
    {
      "name": "Wrapper TX",
      "symbol": "WTX",
      "address": "0xF6c5377251Fa00B086FeCd907b1404aDb2845BB8",
      "chainId": 8989,
      "decimals": 18,
      "logoURI": "https://cdridge.oss-cn-shanghai.aliyuncs.com/telegram_pocket/TX.png"
    },
    {
      "name": "USDT Token",
      "symbol": "USDT",
      "address": "0xC41A356311fC63CaBa3dE686c80a6D4a55ABFFD6",
      "chainId": 8989,
      "decimals": 18,
      "logoURI": "https://raw.githubusercontent.com/trustwallet/assets/master/blockchains/ethereum/assets/0xdAC17F958D2ee523a2206206994597C13D831ec7/logo.png"
    }
  ]
}
